README.rst
setup.py
neuronunit/__init__.py
neuronunit/aibs.py
neuronunit/bbp.py
neuronunit/neuroelectro.py
neuronunit/plottools.py
neuronunit/capabilities/__init__.py
neuronunit/capabilities/channel.py
neuronunit/capabilities/spike_functions.py
neuronunit/models/__init__.py
neuronunit/models/channel.py
neuronunit/models/reduced.py
neuronunit/models/section_extension.py
neuronunit/models/backends/__init__.py
neuronunit/models/backends/base.py
neuronunit/models/backends/jNeuroML.py
neuronunit/models/backends/neuron.py
neuronunit/neuroconstruct/__init__.py
neuronunit/neuroconstruct/capabilities.py
neuronunit/neuroconstruct/models.py
neuronunit/optimization/__init__.py
neuronunit/optimization/data_transport_container.py
neuronunit/optimization/exhaustive_search.py
neuronunit/optimization/get_neab.py
neuronunit/optimization/model_parameters.py
neuronunit/optimization/optimization_management.py
neuronunit/tests/__init__.py
neuronunit/tests/base.py
neuronunit/tests/channel.py
neuronunit/tests/dynamics.py
neuronunit/tests/fi.py
neuronunit/tests/passive.py
neuronunit/tests/waveform.py
neuronunit/unit_test/__init__.py
neuronunit/unit_test/__main__.py
neuronunit/unit_test/base.py
neuronunit/unit_test/data_transport_container.py
neuronunit/unit_test/doc_tests.py
neuronunit/unit_test/exhaustive_search.py
neuronunit/unit_test/import_tests.py
neuronunit/unit_test/launch_tests.py
neuronunit/unit_test/misc_tests.py
neuronunit/unit_test/model_parameters.py
neuronunit/unit_test/model_tests.py
neuronunit/unit_test/neuroconstruct_tests.py
neuronunit/unit_test/openworm_tests.py
neuronunit/unit_test/optimization_tests.py
neuronunit/unit_test/resource_tests.py
neuronunit/unit_test/sciunit_tests.py
neuronunit/unit_test/showcase_tests.py
neuronunit/unit_test/test_auxillary.py
neuronunit/unit_test/test_auxillary_unit.py
neuronunit/unit_test/test_optimization.py
neuronunit/unit_test/test_tests.py
scidash_api/__init__.py
scidash_api/client.py
scidash_api/exceptions.py
scidash_api/helper.py
scidash_api.egg-info/PKG-INFO
scidash_api.egg-info/SOURCES.txt
scidash_api.egg-info/dependency_links.txt
scidash_api.egg-info/requires.txt
scidash_api.egg-info/top_level.txt
